topsis_harnoor_102303260/__init__.py
topsis_harnoor_102303260-0.1.1.dist-info/WHEEL
topsis_harnoor_102303260-0.1.1.dist-info/entry_points.txt
topsis_harnoor_102303260-0.1.1.dist-info/METADATA
topsis_harnoor_102303260-0.1.1.dist-info/RECORD
