Metadata-Version: 2.3
Name: topsis-harnoor-102303260
Version: 0.1.1
Summary: A package implement TOPSIS from scratch.
Author: Harnoor Singh
Author-email: Harnoor Singh <sharnoor998@gmail.com>
Requires-Dist: argparse>=1.4.0
Requires-Dist: pandas>=2.3.3
Requires-Dist: pyxlsx>=1.1.3
Requires-Python: >=3.11
